discord/ext/menus/__init__.py
discord_ext_hybrid_menus-1.0.3.dist-info/LICENSE
discord_ext_hybrid_menus-1.0.3.dist-info/METADATA
discord_ext_hybrid_menus-1.0.3.dist-info/WHEEL
discord_ext_hybrid_menus-1.0.3.dist-info/top_level.txt
discord_ext_hybrid_menus-1.0.3.dist-info/RECORD
